vcolor/__init__.py
vcolor/algorithms.py
vcolor_package-0.1.dist-info/LICENSE.TXT
vcolor_package-0.1.dist-info/METADATA
vcolor_package-0.1.dist-info/WHEEL
vcolor_package-0.1.dist-info/top_level.txt
vcolor_package-0.1.dist-info/RECORD
