Metadata-Version: 2.1
Name: vcolor-package
Version: 0.1
Summary: Graph Coloring Algorithms
Home-page: http://google.com/vcolor_package
Author: Shruti Jiwatode
Author-email: shrutijiwatode1997@gmail.com
License: UCC
Keywords: Coloring Algorithms
License-File: LICENSE.TXT
